{"answers":["agatizing","agnizing","anticizing","anziani","atticizing","azan","gazang","gazanging","gazania","gazing","gizz","izzat","tazza","tizz","tzitzit","zagging","zanana","zanza","zati","zigan","zigging","zigzag","zigzagging","zinc","zincic","zincing","zing","zingani","zinging","zinnia","ziti","zizania","zizit","zizz","zizzing"],"centerLetter":"z","letterString":"zacgint","outerLetters":["a","c","g","i","n","t"],"pangrams":["anticizing","atticizing"],"validLetters":["a","c","g","i","n","t","z"]}
